{
  "transactions": [
    {
      "description": "Desenvolvimento de app",
      "type": "income",
      "category": "Venda",
      "price": 10000,
      "createdAt": "2023-02-22T04:26:59.435Z",
      "id": 1
    },
    {
      "description": "Sanduíche",
      "type": "expense",
      "category": "Alimentação",
      "price": 30,
      "createdAt": "2023-02-22T04:29:34.343Z",
      "id": 2
    },
    {
      "description": "Curso de Figma Rocketseat",
      "type": "expense",
      "category": "Educação",
      "price": 500,
      "createdAt": "2023-02-22T04:30:13.083Z",
      "id": 3
    }
  ]
}